odoo/addons/product_meat_unece/README.rst
odoo/addons/product_meat_unece/__init__.py
odoo/addons/product_meat_unece/__manifest__.py
odoo/addons/product_meat_unece/data/unece_code_list.xml
odoo/addons/product_meat_unece/i18n/fr.po
odoo/addons/product_meat_unece/i18n/product_meat_unece.pot
odoo/addons/product_meat_unece/models/__init__.py
odoo/addons/product_meat_unece/models/product_template.py
odoo/addons/product_meat_unece/models/unece_code_list.py
odoo/addons/product_meat_unece/readme/CONTRIBUTORS.rst
odoo/addons/product_meat_unece/readme/DESCRIPTION.rst
odoo/addons/product_meat_unece/readme/ROADMAP.rst
odoo/addons/product_meat_unece/readme/USAGE.rst
odoo/addons/product_meat_unece/static/description/icon.png
odoo/addons/product_meat_unece/static/description/index.html
odoo/addons/product_meat_unece/tests/__init__.py
odoo/addons/product_meat_unece/tests/test_product_meat_unece.py
odoo/addons/product_meat_unece/views/product_template.xml
odoo13_addon_product_meat_unece-13.0.1.0.1.dev5.dist-info/METADATA
odoo13_addon_product_meat_unece-13.0.1.0.1.dev5.dist-info/WHEEL
odoo13_addon_product_meat_unece-13.0.1.0.1.dev5.dist-info/top_level.txt
odoo13_addon_product_meat_unece-13.0.1.0.1.dev5.dist-info/RECORD
