Metadata-Version: 2.1
Name: odoo13-addon-product-meat-unece
Version: 13.0.1.0.1.dev5
Summary: This module adds the UNECE Meat Carcasses and Cuts Classification.
Home-page: https://github.com/OCA/community-data-files
Author: ACSONE SA/NV,Odoo Community Association (OCA)
Author-email: support@odoo-community.org
License: AGPL-3
Platform: UNKNOWN
Classifier: Programming Language :: Python
Classifier: Framework :: Odoo
Classifier: Framework :: Odoo :: 13.0
Classifier: License :: OSI Approved :: GNU Affero General Public License v3
Requires-Python: >=3.5
Requires-Dist: odoo13-addon-base-unece
Requires-Dist: odoo <13.1dev,>=13.0a
